Metadata-Version: 2.1
Name: dingtalk-stream-wsproxy
Version: 0.15.5
Summary: A Python library for sending messages to DingTalk chatbot, which supports http prxoy for websocket
Home-page: https://github.com/hjwforever/dingtalk-stream-sdk-python
Author: hjwforever
Author-email: hjwbelieve@gmail.com
License: MIT
Platform: UNKNOWN
Classifier: Development Status :: 3 - Alpha
Classifier: Intended Audience :: Developers
Classifier: License :: OSI Approved :: MIT License
Classifier: Programming Language :: Python :: 3
Classifier: Programming Language :: Python :: 3.6
Classifier: Programming Language :: Python :: 3.7
Classifier: Programming Language :: Python :: 3.8
Classifier: Programming Language :: Python :: 3.9
Classifier: Programming Language :: Python :: Implementation :: CPython
Classifier: Programming Language :: Python :: Implementation :: PyPy
License-File: LICENSE
Requires-Dist: aiohttp (>=3.9.1)
Requires-Dist: requests (>=2.27.1)
Requires-Dist: urllib3 (==1.26.15)
Requires-Dist: websockets (>=11.0.2)
